[
{
"id" : "1",
"usetitle" : "테스트용",
"useDeta" : "달 밝은 밤 야행을 즐길 수 있어 즐거웠습니다."
},
{
"id" : "2",
"usetitle" : "제목",
"useDeta" : "주저리주저리",
"img" : ""
},
{
"id" : "3",
"usetitle" : "제목",
"useDeta" : "주저리주저리",
"img" : ""
},
{
"id" : "4",
"usetitle" : "제목",
"useDeta" : "주저리주저리",
"img" : ""
},
{
"id" : "5",
"usetitle" : "제목",
"useDeta" : "주저리주저리",
"img" : ""
},
{
"id" : "6",
"usetitle" : "제목",
"useDeta" : "주저리주저리",
"img" : ""
},
{
"id" : "7",
"usetitle" : "제목",
"useDeta" : "주저리주저리",
"img" : ""
},
{
"id" : "8",
"usetitle" : "제목",
"useDeta" : "주저리주저리",
"img" : ""
},
{
"id" : "9",
"usetitle" : "제목",
"useDeta" : "주저리주저리",
"img" : ""
},
{
"id" : "10",
"usetitle" : "제목",
"useDeta" : "주저리주저리",
"img" : ""    
},
{
"id" : "11",
"usetitle" : "제목",
"useDeta" : "주저리주저리",
"img" : ""
},
{
"id" : "12",
"usetitle" : "제목",
"useDeta" : "주저리주저리",
"img" : ""
},
{
"id" : "13",
"usetitle" : "제목",
"useDeta" : "주저리주저리",
"img" : ""   
},
{
"id" : "14",
"usetitle" : "제목",
"useDeta" : "주저리주저리",
"img" : ""    
},
{
"id" : "15",
"usetitle" : "제목",
"useDeta" : "주저리주저리",
"img" : ""    
},
{
"id" : "16",
"usetitle" : "제목",
"useDeta" : "주저리주저리",
"img" : ""
},
{
"id" : "17",
"usetitle" : "제목",
"useDeta" : "주저리주저리",
"img" : ""    
},
{
"id" : "12",
"usetitle" : "제목",
"useDeta" : "주저리주저리",
"img" : ""
}
]